Modulo_verificacao_de_paridade/v_paridade.v
module verificador_paridade (
    input wire b1,b2,b3,b4,b5,bp,
    output wire S
);
    assign S=~(b1^b2^b3^b4^b5^bp); //xnor
    
endmodule

Modulo_display/Codigo/display.v
`include "../../Modulo_verificacao_de_paridade/Codigo/v_paridade.v"

module display_7_seg (b1,b2,b3,b4,b5,b_par,A,B,C,D,E,F,G);
    input b1,b2,b3,b4,b5,b_par,S;
    output reg A,B,C,D,E,F,G;

    //instanciacao do modulo de verificacao de paridade
    verificador_paridade verifica(b1,b2,b3,b4,b5,b_par,S);

    always@(*) begin
        //verifica se a paridade está incorreta para exibir o carctere especial
        if(S == 1'b0)begin
            A <= 1'b1;
            B <= 1'b1;
            C <= 1'b1;
            D <= 1'b1;
            E <= 1'b1;
            F <= 1'b1;
            G <= 1'b1;

        end
        //verifica se as string de bits está dentro do intervalo que forma os 20 caracteres
        else if ((b1 == 1'b1 & b2 == 1'b1) | b1 == 1'b1 & b3 == 1'b1)begin
            A <= 1'b0;
            B <= 1'b0;
            C <= 1'b0;
            D <= 1'b0;
            E <= 1'b0;
            F <= 1'b0;
            G <= 1'b0;
        end
        //caso a paridade esteja correta e a mensagem esteja dentro do intervalo, será exibido o caractere correspondente
        else if(S == 1'b1)begin
            A <= (((~b1) & b4 & (~b5)) | ((~b1) & b2 & b3) | ((~b1) & b3 & (~b5)) | ((~b1) & b2 & (~b5)));
            B <= (((~b1) & b4 & b5) | ((~b1) & b2 & b5) | ((~b1) & (~b2) & b3 & (~b5)) | (~b1) & b2 & (~b3) & (~b4) | (b1 & (~b2) & (~b3) & b4 & (~b5)));
            C <= (((~b1) & (~b4) & (~b5)) | ((~b1) & b4 & b5) | ((~b1) & b2 & (~b3)) | ((~b1) & b2 & (~b4)) | ((~b2) & (~b3) & (~b4) & b5));
            D <= (((~b2) & (~b3) & (~b5)) | ((~b1) & (~b2) & (~b3) & (~b4)) | ((~b1) & b3 & b4 & b5) | ((~b1) & b2 & b3 & b4) | ((~b1) & b2 & (~b4) & (~b5)));;
            E <= (((~b1) & b2 & (~b3)) | ((~b1) & b4 & (~b5)) | ((~b2) & (~b3) & (~b4)) | ((~b1) & (~b2) & (~b4) & b5) | (b1 & (~b2) & (~b3) & b5));
            F <= (((~b1) & b2 & (~b4)) | ((~b1) & b2 & b5) | ((~b1) & b3 & b4) | ((~b1) & (~b2) & b4 & (~b5)) | ((~b1) & (~b3) & (~b4) & b5) | (b1 & (~b2) & (~b3) & (~b5)) | (b1 & (~b2) & (~b3) & b4));
            G <= (((~b1) & (~b4) & b5) | ((~b1) & b3 & b5) | ((~b1) & b2 & b5) | ((~b1) & (~b2) & b4 & (~b5)) | ((~b1) & b2 & b3 &(~b4)) | (b1 & (~b2) & (~b3) & (~b4)));
        end
    end
endmodule

Modulo_display/Codigo/display_tb.v
`include "./display.v"

module display_tb();

    wire A,B,C,D,E,F,G;
    reg b1,b2,b3,b4,b5,b_par;

    //instancia o módulo de display de forma a enviar estímulos e receber as saídas
    display_7_seg tb_display(b1,b2,b3,b4,b5,b_par,A,B,C,D,E,F,G);


    initial begin
        //gera o arquivo para visualizar a forma de ondas
        $dumpfile("display.vcd");
        $dumpvars;
        $display("b1 b2 b3 b4 b5 b_par-A B C D E F G");
        //monitora as variações nas variáveis e exibe no terminal
        $monitor("%b  %b  %b  %b  %b  %b     %b %b %b %b %b %b %b",b1,b2,b3,b4,b5,b_par,A,B,C,D,E,F,G);

        b1= 1'b0; b2= 1'b0; b3= 1'b0; b4= 1'b0; b5= 1'b0; b_par= 1'b0;
        #10
        b1= 1'b0; b2= 1'b0; b3= 1'b0; b4= 1'b0; b5= 1'b0; b_par= 1'b1;
        #10
        b1= 1'b0; b2= 1'b0; b3= 1'b0; b4= 1'b0; b5= 1'b1; b_par= 1'b0;
        #10 
        b1= 1'b0; b2= 1'b0; b3= 1'b0; b4= 1'b0; b5= 1'b1; b_par= 1'b1;
        #10 
        b1= 1'b0; b2= 1'b0; b3= 1'b0; b4= 1'b1; b5= 1'b0; b_par= 1'b0;
        #10 
        b1= 1'b0; b2= 1'b0; b3= 1'b0; b4= 1'b1; b5= 1'b0; b_par= 1'b1;
        #10 
        b1= 1'b0; b2= 1'b0; b3= 1'b0; b4= 1'b1; b5= 1'b1; b_par= 1'b0;
        #10 
        b1= 1'b0; b2= 1'b0; b3= 1'b0; b4= 1'b1; b5= 1'b1; b_par= 1'b1;
        #10 
        b1= 1'b0; b2= 1'b0; b3= 1'b1; b4= 1'b0; b5= 1'b0; b_par= 1'b0;
        #10 
        b1= 1'b0; b2= 1'b0; b3= 1'b1; b4= 1'b0; b5= 1'b0; b_par= 1'b1;
        #10 
        b1= 1'b0; b2= 1'b0; b3= 1'b1; b4= 1'b0; b5= 1'b1; b_par= 1'b0;
        #10 
        b1= 1'b0; b2= 1'b0; b3= 1'b1; b4= 1'b0; b5= 1'b1; b_par= 1'b1;
        #10 
        b1= 1'b0; b2= 1'b0; b3= 1'b1; b4= 1'b1; b5= 1'b0; b_par= 1'b0;
        #10 
        b1= 1'b0; b2= 1'b0; b3= 1'b1; b4= 1'b1; b5= 1'b0; b_par= 1'b1;
        #10 
        b1= 1'b0; b2= 1'b0; b3= 1'b1; b4= 1'b1; b5= 1'b1; b_par= 1'b0;
        #10 
        b1= 1'b0; b2= 1'b0; b3= 1'b1; b4= 1'b1; b5= 1'b1; b_par= 1'b1;
        #10 

        b1= 1'b0; b2= 1'b1; b3= 1'b0; b4= 1'b0; b5= 1'b0; b_par= 1'b0;
        #10
        b1= 1'b0; b2= 1'b1; b3= 1'b0; b4= 1'b0; b5= 1'b0; b_par= 1'b1;
        #10
        b1= 1'b0; b2= 1'b1; b3= 1'b0; b4= 1'b0; b5= 1'b1; b_par= 1'b0;
        #10
        b1= 1'b0; b2= 1'b1; b3= 1'b0; b4= 1'b0; b5= 1'b1; b_par= 1'b1;
        #10 
        b1= 1'b0; b2= 1'b1; b3= 1'b0; b4= 1'b1; b5= 1'b0; b_par= 1'b0;
        #10 
        b1= 1'b0; b2= 1'b1; b3= 1'b0; b4= 1'b1; b5= 1'b0; b_par= 1'b1;
        #10
        b1= 1'b0; b2= 1'b1; b3= 1'b0; b4= 1'b1; b5= 1'b1; b_par= 1'b0;
        #10
        b1= 1'b0; b2= 1'b1; b3= 1'b0; b4= 1'b1; b5= 1'b1; b_par= 1'b1;
        #10
        b1= 1'b0; b2= 1'b1; b3= 1'b1; b4= 1'b0; b5= 1'b0; b_par= 1'b0;
        #10
        b1= 1'b0; b2= 1'b1; b3= 1'b1; b4= 1'b0; b5= 1'b0; b_par= 1'b1;
        #10
        b1= 1'b0; b2= 1'b1; b3= 1'b1; b4= 1'b0; b5= 1'b1; b_par= 1'b0;
        #10
        b1= 1'b0; b2= 1'b1; b3= 1'b1; b4= 1'b0; b5= 1'b1; b_par= 1'b1;
        #10
        b1= 1'b0; b2= 1'b1; b3= 1'b1; b4= 1'b1; b5= 1'b0; b_par= 1'b0;
        #10
        b1= 1'b0; b2= 1'b1; b3= 1'b1; b4= 1'b1; b5= 1'b0; b_par= 1'b1;
        #10
        b1= 1'b0; b2= 1'b1; b3= 1'b1; b4= 1'b1; b5= 1'b1; b_par= 1'b0;
        #10
        b1= 1'b0; b2= 1'b1; b3= 1'b1; b4= 1'b1; b5= 1'b1; b_par= 1'b1;
        #10

        b1= 1'b1; b2= 1'b0; b3= 1'b0; b4= 1'b0; b5= 1'b0; b_par= 1'b0;
        #10
        b1= 1'b1; b2= 1'b0; b3= 1'b0; b4= 1'b0; b5= 1'b0; b_par= 1'b1;
        #10
        b1= 1'b1; b2= 1'b0; b3= 1'b0; b4= 1'b0; b5= 1'b1; b_par= 1'b0;
        #10
        b1= 1'b1; b2= 1'b0; b3= 1'b0; b4= 1'b0; b5= 1'b1; b_par= 1'b1;
        #10
        b1= 1'b1; b2= 1'b0; b3= 1'b0; b4= 1'b1; b5= 1'b0; b_par= 1'b0;
        #10
        b1= 1'b1; b2= 1'b0; b3= 1'b0; b4= 1'b1; b5= 1'b0; b_par= 1'b1;
        #10
        b1= 1'b1; b2= 1'b0; b3= 1'b0; b4= 1'b1; b5= 1'b1; b_par= 1'b0;
        #10
        b1= 1'b1; b2= 1'b0; b3= 1'b0; b4= 1'b1; b5= 1'b1; b_par= 1'b1;
        #10
        b1= 1'b1; b2= 1'b0; b3= 1'b1; b4= 1'b0; b5= 1'b0; b_par= 1'b0;
        #10
        b1= 1'b1; b2= 1'b0; b3= 1'b1; b4= 1'b0; b5= 1'b0; b_par= 1'b1;
        #10
        b1= 1'b1; b2= 1'b0; b3= 1'b1; b4= 1'b0; b5= 1'b1; b_par= 1'b0;
        #10
        b1= 1'b1; b2= 1'b0; b3= 1'b1; b4= 1'b0; b5= 1'b1; b_par= 1'b1;
        #10
        b1= 1'b1; b2= 1'b0; b3= 1'b1; b4= 1'b1; b5= 1'b0; b_par= 1'b0;
        #10
        b1= 1'b1; b2= 1'b0; b3= 1'b1; b4= 1'b1; b5= 1'b0; b_par= 1'b1;
        #10
        b1= 1'b1; b2= 1'b0; b3= 1'b1; b4= 1'b1; b5= 1'b1; b_par= 1'b0;
        #10
        b1= 1'b1; b2= 1'b0; b3= 1'b1; b4= 1'b1; b5= 1'b1; b_par= 1'b1;
        #10

        b1= 1'b1; b2= 1'b1; b3= 1'b0; b4= 1'b0; b5= 1'b0; b_par= 1'b0;
        #10
        b1= 1'b1; b2= 1'b1; b3= 1'b0; b4= 1'b0; b5= 1'b0; b_par= 1'b1;
        #10
        b1= 1'b1; b2= 1'b1; b3= 1'b0; b4= 1'b0; b5= 1'b1; b_par= 1'b0;
        #10
        b1= 1'b1; b2= 1'b1; b3= 1'b0; b4= 1'b0; b5= 1'b1; b_par= 1'b1;
        #10
        b1= 1'b1; b2= 1'b1; b3= 1'b0; b4= 1'b1; b5= 1'b0; b_par= 1'b0;
        #10
        b1= 1'b1; b2= 1'b1; b3= 1'b0; b4= 1'b1; b5= 1'b0; b_par= 1'b1;
        #10
        b1= 1'b1; b2= 1'b1; b3= 1'b0; b4= 1'b1; b5= 1'b1; b_par= 1'b0;
        #10
        b1= 1'b1; b2= 1'b1; b3= 1'b0; b4= 1'b1; b5= 1'b1; b_par= 1'b1;
        #10
        b1= 1'b1; b2= 1'b1; b3= 1'b1; b4= 1'b0; b5= 1'b0; b_par= 1'b0;
        #10
        b1= 1'b1; b2= 1'b1; b3= 1'b1; b4= 1'b0; b5= 1'b0; b_par= 1'b1;
        #10
        b1= 1'b1; b2= 1'b1; b3= 1'b1; b4= 1'b0; b5= 1'b1; b_par= 1'b0;
        #10
        b1= 1'b1; b2= 1'b1; b3= 1'b1; b4= 1'b0; b5= 1'b1; b_par= 1'b1;
        #10
        b1= 1'b1; b2= 1'b1; b3= 1'b1; b4= 1'b1; b5= 1'b0; b_par= 1'b0;
        #10
        b1= 1'b1; b2= 1'b1; b3= 1'b1; b4= 1'b1; b5= 1'b0; b_par= 1'b1;
        #10
        b1= 1'b1; b2= 1'b1; b3= 1'b1; b4= 1'b1; b5= 1'b1; b_par= 1'b0;
        #10
        b1= 1'b1; b2= 1'b1; b3= 1'b1; b4= 1'b1; b5= 1'b1; b_par= 1'b1;
        #10
        

        
        #10$finish;
    end
endmodule

Modulo_display/Codigo/display.vcd
$date
	Mon Nov 25 18:33:05 2024
$end
$version
	Icarus Verilog
$end
$timescale
	1s
$end
$scope module display_tb $end
$var wire 1 ! G $end
$var wire 1 " F $end
$var wire 1 # E $end
$var wire 1 $ D $end
$var wire 1 % C $end
$var wire 1 & B $end
$var wire 1 ' A $end
$var reg 1 ( b1 $end
$var reg 1 ) b2 $end
$var reg 1 * b3 $end
$var reg 1 + b4 $end
$var reg 1 , b5 $end
$var reg 1 - b_par $end
$scope module tb_display $end
$var wire 1 ( b1 $end
$var wire 1 ) b2 $end
$var wire 1 * b3 $end
$var wire 1 + b4 $end
$var wire 1 , b5 $end
$var wire 1 - b_par $end
$var wire 1 . S $end
$var reg 1 ' A $end
$var reg 1 & B $end
$var reg 1 % C $end
$var reg 1 $ D $end
$var reg 1 # E $end
$var reg 1 " F $end
$var reg 1 ! G $end
$scope module verifica $end
$var wire 1 . S $end
$var wire 1 ( b1 $end
$var wire 1 ) b2 $end
$var wire 1 * b3 $end
$var wire 1 + b4 $end
$var wire 1 , b5 $end
$var wire 1 - bp $end
$upscope $end
$upscope $end
$upscope $end
$enddefinitions $end
#0
$dumpvars
1.
0-
0,
0+
0*
0)
0(
0'
0&
1%
1$
1#
0"
0!
$end
#10
1!
1"
1&
1'
0.
1-
#20
0-
1,
#30
0&
0'
1.
1-
#40
1&
1%
1'
0.
0-
0,
1+
#50
0%
0&
1.
1-
#60
0!
0"
0#
0$
1%
1&
0'
0-
1,
#70
1!
1"
1#
1$
1'
0.
1-
#80
0-
0,
0+
1*
#90
0!
0"
0#
0$
1.
1-
#100
1!
1#
0%
0&
0'
0-
1,
#110
1"
1$
1%
1&
1'
0.
1-
#120
0$
0%
1.
0-
0,
1+
#130
1$
1%
0.
1-
#140
0-
1,
#150
0#
0'
1.
1-
#160
1!
1#
1'
0.
0-
0,
0+
0*
1)
#170
0!
1.
1-
#180
1!
0$
0'
0-
1,
#190
1$
1'
0.
1-
#200
0!
0"
0$
0&
1.
0-
0,
1+
#210
1!
1"
1$
1&
0.
1-
#220
0-
1,
#230
0$
0'
1.
1-
#240
0#
1$
0&
1'
0-
0,
0+
1*
#250
1#
1&
0.
1-
#260
0-
1,
#270
0#
0$
1.
1-
#280
1!
1#
1$
1%
1&
0.
0-
0,
1+
#290
0!
0%
0&
1.
1-
#300
1!
0#
1%
1&
0-
1,
#310
1#
0.
1-
#320
0-
0,
0+
0*
0)
1(
#330
0%
0&
0'
1.
1-
#340
0"
0$
1%
0-
1,
#350
1"
1$
1&
1'
0.
1-
#360
0!
0#
0%
0'
1.
0-
0,
1+
#370
1!
1#
1%
1'
0.
1-
#380
0-
1,
#390
0!
0$
0%
0&
0'
1.
1-
#400
0"
0#
0-
0,
0+
1*
#410
1!
1"
1#
1$
1%
1&
1'
0.
1-
#420
0-
1,
#430
0!
0"
0#
0$
0%
0&
0'
1.
1-
#440
1!
1"
1#
1$
1%
1&
1'
0.
0-
0,
1+
#450
0!
0"
0#
0$
0%
0&
0'
1.
1-
#460
0-
1,
#470
1!
1"
1#
1$
1%
1&
1'
0.
1-
#480
0!
0"
0#
0$
0%
0&
0'
1.
0-
0,
0+
0*
1)
#490
1!
1"
1#
1$
1%
1&
1'
0.
1-
#500
0-
1,
#510
0!
0"
0#
0$
0%
0&
0'
1.
1-
#520
1!
1"
1#
1$
1%
1&
1'
0.
0-
0,
1+
#530
0!
0"
0#
0$
0%
0&
0'
1.
1-
#540
0-
1,
#550
1!
1"
1#
1$
1%
1&
1'
0.
1-
#560
0-
0,
0+
1*
#570
0!
0"
0#
0$
0%
0&
0'
1.
1-
#580
0-
1,
#590
1!
1"
1#
1$
1%
1&
1'
0.
1-
#600
0!
0"
0#
0$
0%
0&
0'
1.
0-
0,
1+
#610
1!
1"
1#
1$
1%
1&
1'
0.
1-
#620
0-
1,
#630
0!
0"
0#
0$
0%
0&
0'
1.
1-
